cf_helper/__init__.py
cf_helper/display.py
cf_helper/utility.py
cf_helper-0.2.2.dist-info/LICENSE
cf_helper-0.2.2.dist-info/METADATA
cf_helper-0.2.2.dist-info/WHEEL
cf_helper-0.2.2.dist-info/top_level.txt
cf_helper-0.2.2.dist-info/RECORD
