Metadata-Version: 2.1
Name: cf-helper
Version: 0.2.2
Summary: A Python library for interacting with Codeforces API and automating tasks.
Home-page: https://github.com/skv-1180/CF-Automate
Author: Shubham Kumar Verma
Author-email: skv.iitroorkee@gmail.com
Classifier: Programming Language :: Python :: 3
Classifier: License :: OSI Approved :: MIT License
Classifier: Operating System :: OS Independent
Requires-Python: >=3.6
License-File: LICENSE
Requires-Dist: requests
Requires-Dist: python-dotenv==0.20.0
